bvn_values/__init__.py
bvn_values/__main__.py
bvn_values/values.py
bvn_values-0.1.1.dist-info/LICENSE
bvn_values-0.1.1.dist-info/WHEEL
bvn_values-0.1.1.dist-info/METADATA
bvn_values-0.1.1.dist-info/RECORD
