Metadata-Version: 2.1
Name: bvn_values
Version: 0.1.1
Summary: BVN specific values and functions and things.
Author-email: Ben Doherty <ben_doherty@bvn.com.au>
Classifier: License :: OSI Approved :: MIT License
Project-URL: Home, https://github.com/bvn-architecture/py-brand
